odoo/addons/base_substate/README.rst
odoo/addons/base_substate/__init__.py
odoo/addons/base_substate/__manifest__.py
odoo/addons/base_substate/i18n/base_substate.pot
odoo/addons/base_substate/i18n/it.po
odoo/addons/base_substate/models/__init__.py
odoo/addons/base_substate/models/base_substate.py
odoo/addons/base_substate/models/base_substate_mixin.py
odoo/addons/base_substate/readme/CONTRIBUTORS.rst
odoo/addons/base_substate/readme/DESCRIPTION.rst
odoo/addons/base_substate/readme/USAGE.rst
odoo/addons/base_substate/security/base_substate_security.xml
odoo/addons/base_substate/security/ir.model.access.csv
odoo/addons/base_substate/static/description/icon.png
odoo/addons/base_substate/static/description/index.html
odoo/addons/base_substate/tests/__init__.py
odoo/addons/base_substate/tests/models.py
odoo/addons/base_substate/tests/test_base_substate.py
odoo/addons/base_substate/views/base_substate_type_views.xml
odoo/addons/base_substate/views/base_substate_value_views.xml
odoo/addons/base_substate/views/base_substate_views.xml
odoo14_addon_base_substate-14.0.1.0.1.dev9.dist-info/METADATA
odoo14_addon_base_substate-14.0.1.0.1.dev9.dist-info/WHEEL
odoo14_addon_base_substate-14.0.1.0.1.dev9.dist-info/top_level.txt
odoo14_addon_base_substate-14.0.1.0.1.dev9.dist-info/RECORD
